xia_pattern_xia/__init__.py
xia_pattern_xia/model_pattern.cpython-39-darwin.so
xia_pattern_xia/templates.cpython-39-darwin.so
xia_pattern_xia-0.0.2.dist-info/LICENSE.txt
xia_pattern_xia-0.0.2.dist-info/METADATA
xia_pattern_xia-0.0.2.dist-info/WHEEL
xia_pattern_xia-0.0.2.dist-info/top_level.txt
xia_pattern_xia-0.0.2.dist-info/RECORD
