Metadata-Version: 2.1
Name: xia-pattern-xia
Version: 0.0.2
Summary: UNKNOWN
Home-page: https://develop.x-i-a.com/docs/xia-pattern-xia/0.0.2/index.html
Author: X-I-A
Author-email: admin@x-i-a.com
License: UNKNOWN
Platform: UNKNOWN
Requires-Python: >=3.9
License-File: LICENSE.txt
Requires-Dist: xia-composer
Requires-Dist: xia-compiler-python
